Workbook
Name ClosingCash: 'Cashflow Statement'!$D$32:$F$32
Name NetProfit: 'Profit and Loss'!$D$35:$F$35
Name Revenue: 'Profit and Loss'!$D$10:$F$10
Name TaxRate: Assumptions!$D$32
Name TotalAssets: 'Balance Sheet'!$D$20:$F$20

Sheet Balance Sheet
A1: Northwind Components Ltd. (fictional)
A2: Balance Sheet
A3: As at 31 December ($ in thousands)
D5: FY2023 | E5: FY2024 | F5: FY2025
A7: Assets
B8: Current assets
C9: Cash and cash equivalents | D9: ='Cashflow Statement'!D32 -> 8536.99 | E9: ='Cashflow Statement'!E32 -> 13529.047 | F9: ='Cashflow Statement'!F32 -> 20492.073
C10: Trade receivables | D10: 6120 | E10: 6980 | F10: 7850
C11: Inventories | D11: 4870 | E11: 5310 | F11: 5640
C12: Prepayments | D12: 640 | E12: 700 | F12: 760
C13: Total current assets | D13: =SUM(D9:D12) -> 20166.99 | E13: =SUM(E9:E12) -> 26519.047 | F13: =SUM(F9:F12) -> 34742.073
B15: Non-current assets
C16: Property, plant and equipment | D16: 15400 | E16: =D16-'Cashflow Statement'!E19-'Profit and Loss'!E27 -> 16070 | F16: =E16-'Cashflow Statement'!F19-'Profit and Loss'!F27 -> 16420 | H16: FY2023 opening balances (blue) are inputs; FY2024-25 roll forward
C17: Intangible assets | D17: 2300 | E17: 2450 | F17: 2600
C18: Total non-current assets | D18: =SUM(D16:D17) -> 17700 | E18: =SUM(E16:E17) -> 18520 | F18: =SUM(F16:F17) -> 19020
A20: Total assets | D20: =D13+D18 -> 37866.99 | E20: =E13+E18 -> 45039.047 | F20: =F13+F18 -> 53762.073
A22: Liabilities
B23: Current liabilities
C24: Trade payables | D24: 3980 | E24: 4420 | F24: 4760
C25: Accrued expenses | D25: 1150 | E25: 1240 | F25: 1330
C26: Short-term borrowings | D26: 2000 | E26: 1500 | F26: 1000
C27: Total current liabilities | D27: =SUM(D24:D26) -> 7130 | E27: =SUM(E24:E26) -> 7160 | F27: =SUM(F24:F26) -> 7090
B29: Non-current liabilities
C30: Long-term borrowings | D30: 8500 | E30: 7800 | F30: 7000
C31: Total non-current liabilities | D31: =SUM(D30:D30) -> 8500 | E31: =SUM(E30:E30) -> 7800 | F31: =SUM(F30:F30) -> 7000
A33: Total liabilities | D33: =D27+D31 -> 15630 | E33: =E27+E31 -> 14960 | F33: =F27+F31 -> 14090
A35: Equity
C36: Share capital | D36: 10000 | E36: 10000 | F36: 10000
C37: Retained earnings | D37: 12237 | E37: =D37+'Profit and Loss'!E35+'Cashflow Statement'!E27 -> 20079.057 | F37: =E37+'Profit and Loss'!F35+'Cashflow Statement'!F27 -> 29672.083 | H37: FY2023: the input that balances the sheet
C38: Total equity | D38: =SUM(D36:D37) -> 22237 | E38: =SUM(E36:E37) -> 30079.057 | F38: =SUM(F36:F37) -> 39672.083
A40: Total liabilities and equity | D40: =D33+D38 -> 37867 | E40: =E33+E38 -> 45039.057 | F40: =F33+F38 -> 53762.083
C42: Check: assets less liabilities and equity (should be 0) | D42: =ROUND(D20-D40,0) -> 0 | E42: =ROUND(E20-E40,0) -> 0 | F42: =ROUND(F20-F40,0) -> 0

Sheet Cashflow Statement
A1: Northwind Components Ltd. (fictional)
A2: Cashflow Statement
A3: For the years ended 31 December ($ in thousands)
D5: FY2023 | E5: FY2024 | F5: FY2025
A7: Operating activities
C8: Net profit | D8: ='Profit and Loss'!D35 -> 7946.99 | E8: ='Profit and Loss'!E35 -> 9342.0567 | F8: ='Profit and Loss'!F35 -> 11393.026
C9: Depreciation | D9: ='Profit and Loss'!D27 -> 1620 | E9: ='Profit and Loss'!E27 -> 1780 | F9: ='Profit and Loss'!F27 -> 1950
B10: Changes in working capital
C11: (Increase)/decrease in trade receivables | D11: -520 | E11: ='Balance Sheet'!D10-'Balance Sheet'!E10 -> -860 | F11: ='Balance Sheet'!E10-'Balance Sheet'!F10 -> -870 | H11: FY2023 inputs (blue): no FY2022 balance sheet in this example
C12: (Increase)/decrease in inventories | D12: -310 | E12: ='Balance Sheet'!D11-'Balance Sheet'!E11 -> -440 | F12: ='Balance Sheet'!E11-'Balance Sheet'!F11 -> -330
C13: (Increase)/decrease in prepayments | D13: -40 | E13: ='Balance Sheet'!D12-'Balance Sheet'!E12 -> -60 | F13: ='Balance Sheet'!E12-'Balance Sheet'!F12 -> -60
C14: Increase/(decrease) in trade payables | D14: 280 | E14: ='Balance Sheet'!E24-'Balance Sheet'!D24 -> 440 | F14: ='Balance Sheet'!F24-'Balance Sheet'!E24 -> 340
C15: Increase/(decrease) in accrued expenses | D15: 60 | E15: ='Balance Sheet'!E25-'Balance Sheet'!D25 -> 90 | F15: ='Balance Sheet'!F25-'Balance Sheet'!E25 -> 90
A16: Net cash from operating activities | D16: =SUM(D8:D9)+SUM(D11:D15) -> 9036.99 | E16: =SUM(E8:E9)+SUM(E11:E15) -> 10292.057 | F16: =SUM(F8:F9)+SUM(F11:F15) -> 12513.026
A18: Investing activities
C19: Purchase of property, plant and equipment | D19: -2100 | E19: -2450 | F19: -2300
C20: Purchase of intangible assets | D20: -150 | E20: ='Balance Sheet'!D17-'Balance Sheet'!E17 -> -150 | F20: ='Balance Sheet'!E17-'Balance Sheet'!F17 -> -150
A21: Net cash used in investing activities | D21: =SUM(D19:D20) -> -2250 | E21: =SUM(E19:E20) -> -2600 | F21: =SUM(F19:F20) -> -2450
A23: Financing activities
C24: Proceeds from/(repayment of) short-term borrowings | D24: 500 | E24: ='Balance Sheet'!E26-'Balance Sheet'!D26 -> -500 | F24: ='Balance Sheet'!F26-'Balance Sheet'!E26 -> -500
C25: Proceeds from/(repayment of) long-term borrowings | D25: -700 | E25: ='Balance Sheet'!E30-'Balance Sheet'!D30 -> -700 | F25: ='Balance Sheet'!F30-'Balance Sheet'!E30 -> -800
C26: Proceeds from issue of shares | D26: 0 | E26: ='Balance Sheet'!E36-'Balance Sheet'!D36 -> 0 | F26: ='Balance Sheet'!F36-'Balance Sheet'!E36 -> 0
C27: Dividends paid | D27: -1200 | E27: -1500 | F27: -1800
A28: Net cash from financing activities | D28: =SUM(D24:D27) -> -1400 | E28: =SUM(E24:E27) -> -2700 | F28: =SUM(F24:F27) -> -3100
A30: Net increase/(decrease) in cash | D30: =D16+D21+D28 -> 5386.99 | E30: =E16+E21+E28 -> 4992.0567 | F30: =F16+F21+F28 -> 6963.0258
C31: Cash at the beginning of the year | D31: 3150 | E31: =D32 -> 8536.99 | F31: =E32 -> 13529.047
A32: Cash at the end of the year | D32: =D30+D31 -> 8536.99 | E32: =E30+E31 -> 13529.047 | F32: =F30+F31 -> 20492.073

Sheet Profit and Loss
A1: Northwind Components Ltd. (fictional)
A2: Profit and Loss
A3: For the years ended 31 December ($ in thousands)
D5: FY2023 | E5: FY2024 | F5: FY2025
A7: Revenue
C8: Product sales | D8: ='Revenue Build'!D10 -> 38190 | E8: ='Revenue Build'!E10 -> 42667.777 | F8: ='Revenue Build'!F10 -> 47233.23
C9: Services | D9: ='Revenue Build'!D15 -> 9800 | E9: ='Revenue Build'!E15 -> 11289.6 | F9: ='Revenue Build'!F15 -> 13524
C10: Total revenue | D10: =SUM(D8:D9) -> 47990 | E10: =SUM(E8:E9) -> 53957.377 | F10: =SUM(F8:F9) -> 60757.23
A12: Cost of sales
C13: Materials | D13: ='Cost Build'!D10 -> 17195 | E13: ='Cost Build'!E10 -> 19304.827 | F13: ='Cost Build'!F10 -> 21474.689
C14: Direct labour | D14: ='Cost Build'!D13 -> 7600 | E14: ='Cost Build'!E13 -> 8507.668 | F14: ='Cost Build'!F13 -> 9420.8962
C15: Total cost of sales | D15: =SUM(D13:D14) -> 24795 | E15: =SUM(E13:E14) -> 27812.495 | F15: =SUM(F13:F14) -> 30895.585
A17: Gross profit | D17: =D10-D15 -> 23195 | E17: =E10-E15 -> 26144.883 | F17: =F10-F15 -> 29861.645
C18: Gross margin | D18: =IF(D10=0,0,D17/D10) -> 0.48332986 | E18: =IF(E10=0,0,E17/E10) -> 0.48454696 | F18: =IF(F10=0,0,F17/F10) -> 0.49149121
A20: Operating expenses
B21: Selling and marketing
C22: Advertising | D22: ='Cost Build'!D20 -> 2351.51 | E22: ='Cost Build'!E20 -> 2751.8263 | F22: ='Cost Build'!F20 -> 3098.6187
C23: Sales salaries | D23: ='Cost Build'!D16 -> 3900 | E23: ='Cost Build'!E16 -> 4262.5 | F23: ='Cost Build'!F16 -> 4582
B24: General and administrative
C25: Office rent | D25: ='Cost Build'!D21 -> 1450 | E25: ='Cost Build'!E21 -> 1500 | F25: ='Cost Build'!F21 -> 1560
C26: Administrative salaries | D26: ='Cost Build'!D17 -> 2700 | E26: ='Cost Build'!E17 -> 2883 | F26: ='Cost Build'!F17 -> 3040
C27: Depreciation | D27: 1620 | E27: 1780 | F27: 1950
C28: Total operating expenses | D28: =SUM(D22:D23)+SUM(D25:D27) -> 12021.51 | E28: =SUM(E22:E23)+SUM(E25:E27) -> 13177.326 | F28: =SUM(F22:F23)+SUM(F25:F27) -> 14230.619
A30: Operating profit | D30: =D17-D28 -> 11173.49 | E30: =E17-E28 -> 12967.557 | F30: =F17-F28 -> 15631.026
C31: Interest expense | D31: ='Cost Build'!D25 -> 577.5 | E31: ='Cost Build'!E25 -> 511.5 | F31: ='Cost Build'!F25 -> 440
A32: Profit before tax | D32: =D30-D31 -> 10595.99 | E32: =E30-E31 -> 12456.057 | F32: =F30-F31 -> 15191.026
C33: Income tax | D33: =ROUND(D32*TaxRate,0) -> 2649 | E33: =ROUND(E32*TaxRate,0) -> 3114 | F33: =ROUND(F32*TaxRate,0) -> 3798
A35: Net profit | D35: =D32-D33 -> 7946.99 | E35: =E32-E33 -> 9342.0567 | F35: =F32-F33 -> 11393.026
C36: Net margin | D36: =IF(D10=0,0,D35/D10) -> 0.16559679 | E36: =IF(E10=0,0,E35/E10) -> 0.17313771 | F36: =IF(F10=0,0,F35/F10) -> 0.1875172

Sheet Revenue Build
A1: Northwind Components Ltd. (fictional)
A2: Revenue Build
A3: Product sales and services, from Assumptions ($ in thousands unless stated)
D5: FY2023 | E5: FY2024 | F5: FY2025
A7: Widgets
C8: Units sold | D8: =Assumptions!D8 -> 95000 | E8: =D8*(1+Assumptions!E9) -> 103550 | F8: =E8*(1+Assumptions!F9) -> 111834
C9: Price per widget ($) | D9: =Assumptions!D10 -> 402 | E9: =D9*(1+Assumptions!E11) -> 412.05 | F9: =E9*(1+Assumptions!F11) -> 422.35125
C10: Product sales | D10: =D8*D9/1000 -> 38190 | E10: =E8*E9/1000 -> 42667.777 | F10: =F8*F9/1000 -> 47233.23
A12: Services
C13: Service contracts | D13: =Assumptions!D12 -> 140 | E13: =D13*(1+Assumptions!E13) -> 156.8 | F13: =E13*(1+Assumptions!F13) -> 180.32
C14: Average fee per contract | D14: =Assumptions!D14 -> 70 | E14: =Assumptions!E14 -> 72 | F14: =Assumptions!F14 -> 75
C15: Service revenue | D15: =D13*D14 -> 9800 | E15: =E13*E14 -> 11289.6 | F15: =F13*F14 -> 13524
A17: Total revenue | D17: =D10+D15 -> 47990 | E17: =E10+E15 -> 53957.377 | F17: =F10+F15 -> 60757.23

Sheet Cost Build
A1: Northwind Components Ltd. (fictional)
A2: Cost Build
A3: Costs and interest, from Assumptions, Revenue Build and Balance Sheet ($ in thousands)
D5: FY2023 | E5: FY2024 | F5: FY2025
A7: Cost of sales
C8: Units sold | D8: ='Revenue Build'!D8 -> 95000 | E8: ='Revenue Build'!E8 -> 103550 | F8: ='Revenue Build'!F8 -> 111834
C9: Material cost per widget ($) | D9: =Assumptions!D17 -> 181 | E9: =D9*(1+Assumptions!E18) -> 186.43 | F9: =E9*(1+Assumptions!F18) -> 192.0229
C10: Materials | D10: =D8*D9/1000 -> 17195 | E10: =E8*E9/1000 -> 19304.827 | F10: =F8*F9/1000 -> 21474.689
C12: Labour hours (thousands) | D12: =D8*Assumptions!D19/1000 -> 76 | E12: =E8*Assumptions!E19/1000 -> 81.8045 | F12: =F8*Assumptions!F19/1000 -> 87.23052
C13: Direct labour | D13: =D12*Assumptions!D20 -> 7600 | E13: =E12*Assumptions!E20 -> 8507.668 | F13: =F12*Assumptions!F20 -> 9420.8962
A15: Salaries
C16: Sales salaries | D16: =Assumptions!D23*Assumptions!D25 -> 3900 | E16: =Assumptions!E23*Assumptions!E25 -> 4262.5 | F16: =Assumptions!F23*Assumptions!F25 -> 4582
C17: Administrative salaries | D17: =Assumptions!D24*Assumptions!D26 -> 2700 | E17: =Assumptions!E24*Assumptions!E26 -> 2883 | F17: =Assumptions!F24*Assumptions!F26 -> 3040
A19: Other operating expenses
C20: Advertising | D20: ='Revenue Build'!D17*Assumptions!D29 -> 2351.51 | E20: ='Revenue Build'!E17*Assumptions!E29 -> 2751.8263 | F20: ='Revenue Build'!F17*Assumptions!F29 -> 3098.6187
C21: Office rent | D21: =Assumptions!D30 -> 1450 | E21: =Assumptions!E30 -> 1500 | F21: =Assumptions!F30 -> 1560
A23: Interest
C24: Borrowings at year end | D24: ='Balance Sheet'!D26+'Balance Sheet'!D30 -> 10500 | E24: ='Balance Sheet'!E26+'Balance Sheet'!E30 -> 9300 | F24: ='Balance Sheet'!F26+'Balance Sheet'!F30 -> 8000
C25: Interest expense | D25: =D24*Assumptions!D31 -> 577.5 | E25: =E24*Assumptions!E31 -> 511.5 | F25: =F24*Assumptions!F31 -> 440

Sheet Assumptions
A1: Northwind Components Ltd. (fictional)
A2: Assumptions
A3: Inputs behind Profit and Loss (all fictional)
D5: FY2023 | E5: FY2024 | F5: FY2025
A7: Sales
C8: Widgets sold, FY2023 (units) | D8: 95000
C9: Volume growth | E9: 0.09 | F9: 0.08
C10: Price per widget, FY2023 ($) | D10: 402
C11: Price increase | E11: 0.025 | F11: 0.025
C12: Service contracts, FY2023 | D12: 140
C13: Contract growth | E13: 0.12 | F13: 0.15
C14: Average fee per contract ($000) | D14: 70 | E14: 72 | F14: 75
A16: Costs
C17: Material cost per widget, FY2023 ($) | D17: 181
C18: Material cost inflation | E18: 0.03 | F18: 0.03
C19: Labour hours per widget | D19: 0.8 | E19: 0.79 | F19: 0.78
C20: Labour rate ($ per hour) | D20: 100 | E20: 104 | F20: 108
A22: People
C23: Sales headcount | D23: 52 | E23: 55 | F23: 58
C24: Administrative headcount | D24: 30 | E24: 31 | F24: 32
C25: Average salary, sales ($000) | D25: 75 | E25: 77.5 | F25: 79
C26: Average salary, administrative ($000) | D26: 90 | E26: 93 | F26: 95
A28: Other
C29: Advertising, % of total revenue | D29: 0.049 | E29: 0.051 | F29: 0.051
C30: Office rent ($000) | D30: 1450 | E30: 1500 | F30: 1560
C31: Interest rate on borrowings | D31: 0.055 | E31: 0.055 | F31: 0.055
C32: Income tax rate | D32: 0.25
